{
  "name": "Marc Schmidt",
  "age": 50,
  "address": {
    "street": "Natuhi Parkway",
    "city": "Doljuktu",
    "state": "IN",
    "zip": "75315"
  },
  "contact": {
    "phone": "(559) 367-2503",
    "servicePhone": "800684557"
  },
  "birthday": "1982-09-22T20:32:18.969Z",
  "ip": "125.190.46.157",
  "foo": "bar",
  "profile": {
    "about": "Vuraz rovdoca nan kuvvez sazili jiha sojodna zafouj gasa lozomgav ibuakofiw higto deorojev pu. Poun tilujge rej vaplac gafizju kig zepgondo ugogivot vitiwueda betuno inkabje simif comger ku wiptigdur ori. Zo tew tinerga zavbueba ret vijvetih mahap ve vig eseeje fubkuhbez peagaow kuov rakobtuf hiwiib mobse ufe. Ri hitlijka nocfut ru jusiskim jitgocmak zis fe vuj tekegud nidi vuvoga zowcofmim.",
    "bio": "Obuhosi giaraula dajbuha met enu wub jusit obzihjim votopep kukcacgac otzulzoz dip. Sar ovpap cu baj or fezu lari lice fuwon ebjadi meh naf jito. Pivus copjar joud cuulke dofwe dapjolu im disbuzu unu te ikioconit farizu dobset jelatak surzur. Lil oweovsu ef fewam usa ralwew appukuj ickofmar or buk keempiv za izwargan. Jatsu uco ire toku gozci oh wep nitle nasowa nub hernad da ra. Nusbi jijo ow zaduh miduf dovdihne jamerej ihha fauseno cipucozu eclu bofne. Vow jipsamak betejfe foceof da helef foakja nog bebvorfu cow jino afsapzuh."
  },
  "apiKey": "b79367ce5db49b0dee9fdca843ab83515a6e01c67369d56d9196b0546c6aa338",
  "currency": {
    "code": "BZD",
    "name": "Belize Dollar"
  }
}