{
  "name": "Maria Rodriguez",
  "age": 34,
  "address": {
    "street": "Nekjom Terrace",
    "city": "Revnemac",
    "state": "MA",
    "zip": "30388"
  },
  "contact": {
    "phone": "(322) 360-8612",
    "servicePhone": "800153241"
  },
  "birthday": "1990-01-29T00:04:21.916Z",
  "ip": "107.146.252.188",
  "foo": "bar",
  "profile": {
    "about": "Noajje pibwope epikalze vojveec abeokaru biwuuhu ubde veza veken hid kosisah mepozoma furlo oj geajha ka cud. Vineje ge iz kiarile hohi wi ki ti heduum ver ehrisug suuzku in lu dutgubog. Panwawu de loiti omto abevibek ujo wo fibdidbub holnop duh kahoagu wacoznuj dusse tonig hutpu. He nuecu mefeckoz cezapgac ralamuju lekojfo wezo sobi nuje hac kehfa kugje gemih du ozdum tiwsilo. Fiw mica pa waesho veero da zuk dob ewilu ulacadce ref bikun ora. Wobpuve ni fum lih vakezoeci withabil gocos jaiz ja mevadoz rewdo peciki ge rom. Aromeklu vepko ha pe ra nu tewzilob gusipfe mikias fas tepez igsoh bodusof vi asedova moged ewanofduf hufta.",
    "bio": "Tahzepew turi egsuk andib wamuvi ubulo ozaga je jicadluh dopowsu jaoviwe lu. Itavirwof jum okfek vanec paggasmo nadrirrac donanwuf her faihuvo is gaf akbiwi hil vifce gebutu ezo caivo. Manrire zak bifiwak rikimafe ces konlat wo cutne girfag tamlo ros sikezesu buc rirodeme lapas. Gipusov oda nih vokveda joijo dudjapuh jico saukafo rudumeada ud ro vumpi."
  },
  "apiKey": "9d051a9a71661e2094de43d58890ea72f3f12f951e1b634011dd2bb40114cb77",
  "currency": {
    "code": "MVR",
    "name": "Maldives (Maldive Islands) Rufiyaa"
  }
}