{
  "name": "Gordon Townsend",
  "age": 60,
  "address": {
    "street": "Lomum Ridge",
    "city": "Pibamuvi",
    "state": "DC",
    "zip": "16500"
  },
  "contact": {
    "phone": "(380) 302-2955",
    "servicePhone": "800282541"
  },
  "birthday": "1987-12-13T02:03:47.418Z",
  "ip": "71.179.182.156",
  "foo": "bar",
  "profile": {
    "about": "Ujujafiz wedtudkin ohleuv ihdis usroit getub bu ganpa am vamu ugofaraj rotpu koz bovjih ge devcud gu. Wovoh pagbeage madod natwicenu upe rahin ti ce vacbag ov cooni jiwup vef zogeblam ne onus vipor akikug. Wutnina sopha hatin holozha fohepa seju ike da pabo zozeffa haw cuh jikkig era ikju. Icwoav motrinvik dobotu avgori gid afmir gipegute fub bisuswiz fafna onupavud nugo. Ircib fen ka nu retsoz wuho escugsi pec unanu togtin waene dov ij jebfajo jaksut. Vuco avuudona hofjazlik armowbi kot dir wureis tajaru mer de nog imribben gozohsij ohapufem giv ni gu. Vebso fo ri nu ba wur oke ecre damke ru hakepor polothij fi totip dimjer aneezku.",
    "bio": "Sejra mitoh kupsi rerzew vucviezu jekad ganmazej fa cajvagomi redkil iwa de redta be. Umvujloh pepgewaz wer tulkifjar ovifi posotu bev mas fotzilha cevsu puimu aviike dod. Ejzin ni wora keb aw sinra hovveb zenotu kaw kof mijebuf daruk. Ol nokru tu zigiaz waktep mosofcu nicbut pi jozowsi po en mirta aj eva awvic awenuh fuw. Ur da gu okovapod ekefuvho fe ka wu mowez hetseh ni sem laelo tecvit wujdufe uzo tim bavto. Vah hi lipure gifap jaopa codew ecjic mogwes wob ef kanzozip sa guggomje. Jec un gocorcic rog japicieku ziigeri upurimub we luwagco molsoscu ede tega fasusu."
  },
  "apiKey": "70c9f0648af59fc1256146318cffcdbe4875717241c1d01babd5876e19bfb2e6",
  "currency": {
    "code": "GEL",
    "name": "Georgia Lari"
  }
}