{
  "name": "Amanda Cole",
  "age": 44,
  "address": {
    "street": "Zarbo Way",
    "city": "Casemlep",
    "state": "AK",
    "zip": "07943"
  },
  "contact": {
    "phone": "(249) 422-5387",
    "servicePhone": "800564745"
  },
  "birthday": "1967-06-22T02:17:00.598Z",
  "ip": "67.53.244.190",
  "foo": "bar",
  "profile": {
    "about": "Uwa ci panmu tujub zode okil halovolek rawpium hutcodu rijoiva ababil muvfepvoz haramjuc ludug log iskibsir. Fueg giho jiwveemo vecvulu wa sozmuudi oreno pohlusha tevupij darviaci vep tomuvu disacucu vofmiuko zossijez recbip ah. Mo wedidih abvabo rahuj oza ogbidce saroguh buf da tudfozaj ipi dibewiine nob ji. Fepbuz sez nu ti jolku jercufte embo ca junawkuc mup za miov pe buf. Cukjubhim junfizuw potu usla nabbamer zuur vizif til gubco feh natnowu ukajatijo.",
    "bio": "Je okaboab puwivlon iskob fumew muwwip peeragu ete nojo bim wah si ejzoluka anjiw eh foringez fek muihi. Lahimpit raog vozmueh pahuvi odouna jijuhac wugup venrecaf covuhe pomkaji jujdigra ni sivipgu pinracto luperol ce jovamove. Wedsad zakuzo geruz fah rier es icised kezhetet faca pez neanicu zickavi og wuzno vucvate soc kahtodo horbik. Ejmif avlukan rojterak madgulro ma osu hute ritpaguj bewhabru dupraf vagmobre wezbew beca nocgaupu sud vuopuse hen."
  },
  "apiKey": "ce1fa3b492939abbd26eb6074f716251a1c431a1ad5711e3f867ea47188638f3",
  "currency": {
    "code": "KYD",
    "name": "Cayman Islands Dollar"
  }
}